start_django/__init__.py
start_django/main.py
start_django/version.py
start_django-0.1.1b0.dist-info/LICENSE
start_django-0.1.1b0.dist-info/METADATA
start_django-0.1.1b0.dist-info/WHEEL
start_django-0.1.1b0.dist-info/entry_points.txt
start_django-0.1.1b0.dist-info/top_level.txt
start_django-0.1.1b0.dist-info/RECORD
