Metadata-Version: 2.1
Name: start_django
Version: 0.1.1b0
Summary: A Python wrapper for the OpenWeatherMap API
Home-page: https://github.com/pyaustine/start_django.git
Author: Austine
Author-email: ayahaustine@gmail.com
Classifier: Programming Language :: Python :: 3
Classifier: License :: OSI Approved :: MIT License
Classifier: Operating System :: OS Independent
Requires-Python: >=3.6
License-File: LICENSE
Requires-Dist: Django
